readii/__init__.py
readii/feature_extraction.py
readii/image_processing.py
readii/loaders.py
readii/metadata.py
readii/negative_controls.py
readii/pipeline.py
readii/analyze/__init__.py
readii/analyze/correlation.py
readii/analyze/plot_correlation.py
readii/cli/__init__.py
readii/cli/main.py
readii/data/default_pyradiomics.yaml
readii/io/__init__.py
readii/io/loaders/__init__.py
readii/io/loaders/features.py
readii/io/loaders/general.py
readii/io/loaders/images.py
readii/io/utils/__init__.py
readii/io/utils/pattern_resolver.py
readii/io/writers/README.md
readii/io/writers/__init__.py
readii/io/writers/base_writer.py
readii/io/writers/correlation_writer.py
readii/io/writers/nifti_writer.py
readii/io/writers/plot_writer.py
readii/negative_controls_refactor/README.md
readii/negative_controls_refactor/__init__.py
readii/negative_controls_refactor/__main__.py
readii/negative_controls_refactor/abstract_classes.py
readii/negative_controls_refactor/manager.py
readii/negative_controls_refactor/negative_controls.py
readii/negative_controls_refactor/regions.py
readii/process/__init__.py
readii/process/label.py
readii/process/split.py
readii/process/subset.py
readii/process/config/__init__.py
readii/process/config/dataset_config.py
readii/process/images/__init__.py
readii/process/images/crop.py
readii/utils/__init__.py
readii/utils/logging_config.py
readii/utils/old_logging.py
readii-1.37.0.dist-info/METADATA
readii-1.37.0.dist-info/WHEEL
readii-1.37.0.dist-info/entry_points.txt
readii-1.37.0.dist-info/licenses/LICENSE
readii-1.37.0.dist-info/RECORD
