Metadata-Version: 2.4
Name: readii
Version: 1.37.0
Summary: A package to extract radiomic features!
Author-email: Katy Scott <Katy.Scott@uhn.ca>
License-Expression: MIT
License-File: LICENSE
Classifier: License :: OSI Approved :: MIT License
Classifier: Natural Language :: English
Classifier: Operating System :: OS Independent
Classifier: Programming Language :: Python :: 3.10
Classifier: Programming Language :: Python :: 3.11
Classifier: Programming Language :: Python :: 3.12
Requires-Python: <3.13,>=3.10
Requires-Dist: matplotlib<4,>=3.9.2
Requires-Dist: med-imagetools>=2
Requires-Dist: numpy<3,>=2.2.5
Requires-Dist: orcestra-downloader<1,>=0.9.0
Requires-Dist: pandas<3,>=2.2.3
Requires-Dist: pydicom>=2.3.1
Requires-Dist: pyradiomics-bhklab<4,>=3.1.4
Requires-Dist: seaborn<0.14,>=0.13.2
Requires-Dist: simpleitk>=2.3.1
